cgame/__init__.py
cgame/cgame.cp311-win_amd64.pyd
cgame-1.3.dist-info/licenses/LICENSE.txt
cgame-1.3.dist-info/METADATA
cgame-1.3.dist-info/WHEEL
cgame-1.3.dist-info/top_level.txt
cgame-1.3.dist-info/RECORD
